{
  "2015": [
    {
      "month": "Jan",
      "avgTemp": 15.56
    },
    {
      "month": "Feb",
      "avgTemp": 17.17
    },
    {
      "month": "Mar",
      "avgTemp": 20.29
    },
    {
      "month": "Apr",
      "avgTemp": 22.42
    },
    {
      "month": "May",
      "avgTemp": 26.89
    },
    {
      "month": "Jun",
      "avgTemp": 27.04
    },
    {
      "month": "Jul",
      "avgTemp": 29.5
    },
    {
      "month": "Aug",
      "avgTemp": 31.76
    },
    {
      "month": "Sep",
      "avgTemp": 31.21
    },
    {
      "month": "Oct",
      "avgTemp": 27.22
    },
    {
      "month": "Nov",
      "avgTemp": 23.15
    },
    {
      "month": "Dec",
      "avgTemp": 17.95
    }
  ],
  "2016": [
    {
      "month": "Jan",
      "avgTemp": 15.6
    },
    {
      "month": "Feb",
      "avgTemp": 20.12
    },
    {
      "month": "Mar",
      "avgTemp": 21.64
    },
    {
      "month": "Apr",
      "avgTemp": 26.24
    },
    {
      "month": "May",
      "avgTemp": 26.42
    },
    {
      "month": "Jun",
      "avgTemp": 30.12
    },
    {
      "month": "Jul",
      "avgTemp": 29.92
    },
    {
      "month": "Aug",
      "avgTemp": 31.31
    },
    {
      "month": "Sep",
      "avgTemp": 29.12
    },
    {
      "month": "Oct",
      "avgTemp": 28.07
    },
    {
      "month": "Nov",
      "avgTemp": 22.73
    },
    {
      "month": "Dec",
      "avgTemp": 15.6
    }
  ],
  "2017": [
    {
      "month": "Jan",
      "avgTemp": 15.35
    },
    {
      "month": "Feb",
      "avgTemp": 16.64
    },
    {
      "month": "Mar",
      "avgTemp": 19.49
    },
    {
      "month": "Apr",
      "avgTemp": 23.36
    },
    {
      "month": "May",
      "avgTemp": 26.43
    },
    {
      "month": "Jun",
      "avgTemp": 28.1
    },
    {
      "month": "Jul",
      "avgTemp": 31.2
    },
    {
      "month": "Aug",
      "avgTemp": 30.48
    },
    {
      "month": "Sep",
      "avgTemp": 29.36
    },
    {
      "month": "Oct",
      "avgTemp": 26.64
    },
    {
      "month": "Nov",
      "avgTemp": 22.28
    },
    {
      "month": "Dec",
      "avgTemp": 20.16
    }
  ],
  "2018": [
    {
      "month": "Jan",
      "avgTemp": 16.23
    },
    {
      "month": "Feb",
      "avgTemp": 19.8
    },
    {
      "month": "Mar",
      "avgTemp": 22.71
    },
    {
      "month": "Apr",
      "avgTemp": 23.36
    },
    {
      "month": "May",
      "avgTemp": 28.85
    },
    {
      "month": "Jun",
      "avgTemp": 28.35
    },
    {
      "month": "Jul",
      "avgTemp": 30.0
    },
    {
      "month": "Aug",
      "avgTemp": 29.88
    },
    {
      "month": "Sep",
      "avgTemp": 29.6
    },
    {
      "month": "Oct",
      "avgTemp": 27.39
    },
    {
      "month": "Nov",
      "avgTemp": 22.82
    },
    {
      "month": "Dec",
      "avgTemp": 17.43
    }
  ],
  "2019": [
    {
      "month": "Jan",
      "avgTemp": 15.94
    },
    {
      "month": "Feb",
      "avgTemp": 17.4
    },
    {
      "month": "Mar",
      "avgTemp": 17.88
    },
    {
      "month": "Apr",
      "avgTemp": 21.46
    },
    {
      "month": "May",
      "avgTemp": 28.18
    },
    {
      "month": "Jun",
      "avgTemp": 28.85
    },
    {
      "month": "Jul",
      "avgTemp": 30.11
    },
    {
      "month": "Aug",
      "avgTemp": 30.77
    },
    {
      "month": "Sep",
      "avgTemp": 29.58
    },
    {
      "month": "Oct",
      "avgTemp": 28.19
    },
    {
      "month": "Nov",
      "avgTemp": 25.44
    },
    {
      "month": "Dec",
      "avgTemp": 18.31
    }
  ],
  "2020": [
    {
      "month": "Jan",
      "avgTemp": 14.87
    },
    {
      "month": "Feb",
      "avgTemp": 16.66
    },
    {
      "month": "Mar",
      "avgTemp": 19.96
    },
    {
      "month": "Apr",
      "avgTemp": 21.76
    },
    {
      "month": "May",
      "avgTemp": 27.3
    },
    {
      "month": "Jun",
      "avgTemp": 27.62
    },
    {
      "month": "Jul",
      "avgTemp": 29.81
    },
    {
      "month": "Aug",
      "avgTemp": 30.44
    },
    {
      "month": "Sep",
      "avgTemp": 31.83
    },
    {
      "month": "Oct",
      "avgTemp": 30.14
    },
    {
      "month": "Nov",
      "avgTemp": 23.14
    },
    {
      "month": "Dec",
      "avgTemp": 19.35
    }
  ],
  "2021": [
    {
      "month": "Jan",
      "avgTemp": 18.16
    },
    {
      "month": "Feb",
      "avgTemp": 18.91
    },
    {
      "month": "Mar",
      "avgTemp": 19.41
    },
    {
      "month": "Apr",
      "avgTemp": 23.91
    },
    {
      "month": "May",
      "avgTemp": 28.79
    },
    {
      "month": "Jun",
      "avgTemp": 29.04
    },
    {
      "month": "Jul",
      "avgTemp": 31.77
    },
    {
      "month": "Aug",
      "avgTemp": 33.04
    },
    {
      "month": "Sep",
      "avgTemp": 30.78
    },
    {
      "month": "Oct",
      "avgTemp": 27.82
    },
    {
      "month": "Nov",
      "avgTemp": 25.16
    },
    {
      "month": "Dec",
      "avgTemp": 17.93
    }
  ],
  "2022": [
    {
      "month": "Jan",
      "avgTemp": 15.28
    },
    {
      "month": "Feb",
      "avgTemp": 17.39
    },
    {
      "month": "Mar",
      "avgTemp": 16.07
    },
    {
      "month": "Apr",
      "avgTemp": 25.38
    },
    {
      "month": "May",
      "avgTemp": 26.08
    },
    {
      "month": "Jun",
      "avgTemp": 28.28
    },
    {
      "month": "Jul",
      "avgTemp": 29.92
    },
    {
      "month": "Aug",
      "avgTemp": 30.75
    },
    {
      "month": "Sep",
      "avgTemp": 29.85
    },
    {
      "month": "Oct",
      "avgTemp": 27.54
    },
    {
      "month": "Nov",
      "avgTemp": 23.29
    },
    {
      "month": "Dec",
      "avgTemp": 19.96
    }
  ],
  "2023": [
    {
      "month": "Jan",
      "avgTemp": 18.18
    },
    {
      "month": "Feb",
      "avgTemp": 16.41
    },
    {
      "month": "Mar",
      "avgTemp": 21.31
    },
    {
      "month": "Apr",
      "avgTemp": 23.72
    },
    {
      "month": "May",
      "avgTemp": 26.22
    },
    {
      "month": "Jun",
      "avgTemp": 28.78
    },
    {
      "month": "Jul",
      "avgTemp": 31.53
    },
    {
      "month": "Aug",
      "avgTemp": 31.06
    },
    {
      "month": "Sep",
      "avgTemp": 31.15
    },
    {
      "month": "Oct",
      "avgTemp": 28.98
    },
    {
      "month": "Nov",
      "avgTemp": 24.82
    },
    {
      "month": "Dec",
      "avgTemp": 20.67
    }
  ],
  "2024": [
    {
      "month": "Jan",
      "avgTemp": 17.82
    },
    {
      "month": "Feb",
      "avgTemp": 17.67
    },
    {
      "month": "Mar",
      "avgTemp": 20.81
    },
    {
      "month": "Apr",
      "avgTemp": 25.5
    },
    {
      "month": "May",
      "avgTemp": 26.25
    },
    {
      "month": "Jun",
      "avgTemp": 30.84
    },
    {
      "month": "Jul",
      "avgTemp": 31.48
    },
    {
      "month": "Aug",
      "avgTemp": 31.15
    },
    {
      "month": "Sep",
      "avgTemp": 29.95
    },
    {
      "month": "Oct",
      "avgTemp": 26.9
    },
    {
      "month": "Nov",
      "avgTemp": 22.48
    },
    {
      "month": "Dec",
      "avgTemp": 18.73
    }
  ],
  "2025": [
    {
      "month": "Jan",
      "avgTemp": 18.65
    },
    {
      "month": "Feb",
      "avgTemp": 15.34
    },
    {
      "month": "Mar",
      "avgTemp": 22.24
    }
  ]
}